sys_mcp/__init__.py
sys_mcp/__main__.py
sys_mcp/server.py
sys_mcp/data/blacklist.yml
sys_mcp/tools/__init__.py
sys_mcp/tools/system.py
sys_mcp-0.2.2.dist-info/METADATA
sys_mcp-0.2.2.dist-info/WHEEL
sys_mcp-0.2.2.dist-info/entry_points.txt
sys_mcp-0.2.2.dist-info/RECORD
