Metadata-Version: 2.4
Name: sys-mcp
Version: 0.2.2
Summary: A lightweight MCP server exposing basic system commands for UNIX-like environments.
Author-email: Antriksh Misri <antrikshmisri@gmail.com>
Maintainer-email: Antriksh Misri <antrikshmisri@gmail.com>
Keywords: automation,claude,cli,mcp,server,system,unix
Classifier: Development Status :: 4 - Beta
Classifier: Intended Audience :: Developers
Classifier: License :: OSI Approved :: MIT License
Classifier: Operating System :: MacOS
Classifier: Operating System :: POSIX :: Linux
Classifier: Programming Language :: Python :: 3.12
Classifier: Topic :: Software Development :: Libraries
Classifier: Topic :: System :: Monitoring
Classifier: Topic :: Utilities
Requires-Python: >=3.12
Requires-Dist: httpx>=0.28.1
Requires-Dist: mcp[cli]>=1.18.0
Requires-Dist: pyyaml>=6.0.3
